qview.py
qview-8.0.4.dist-info/METADATA
qview-8.0.4.dist-info/WHEEL
qview-8.0.4.dist-info/entry_points.txt
qview-8.0.4.dist-info/top_level.txt
qview-8.0.4.dist-info/RECORD
