Metadata-Version: 2.1
Name: qview
Version: 8.0.4
Summary: QView visualization and monitoring
Home-page: https://www.state-machine.com/qtools/qview.html
Author: Quantum Leaps
Author-email: info@state-machine.com
License: GPL/commercial
Platform: any
Classifier: Development Status :: 4 - Beta
Classifier: Intended Audience :: Developers
Classifier: Topic :: Software Development :: Embedded Systems
Classifier: Topic :: System :: Monitoring
Classifier: Topic :: System :: Logging
Classifier: License :: OSI Approved :: GNU General Public License v3 or later (GPLv3+)
Classifier: License :: Other/Proprietary License
Classifier: Operating System :: Microsoft :: Windows
Classifier: Operating System :: POSIX :: Linux
Classifier: Operating System :: MacOS :: MacOS X
Classifier: Programming Language :: Python
Classifier: Programming Language :: Python :: 3
